[
  {
    "id": "amazoncanadadealssav",
    "title": "Amazon Canada Deals: Save 42% on Air Purifier + 33% on Wide Flat Iron Hair Straightener + More",
    "imageUrl": "/placeholder-deal.svg",
    "price": 80.64,
    "originalPrice": 106.98,
    "discountPercent": 24,
    "category": "General",
    "description": "\ud83c\udfc6 Top-rated Amazon Canada Deals: Save 42% on Air Purifier + 33% on Wide Flat Iron Hair Straightener + More at a fantastic price. Your wallet will thank you!",
    "affiliateUrl": "https://amazon.ca/",
    "featured": true,
    "dateAdded": "2025-08-07"
  },
  {
    "id": "amazoncanadadealssav",
    "title": "Amazon Canada Deals: Save 33% on Mini Chainsaw + 50% on Women\u2019s Shirts + More",
    "imageUrl": "/placeholder-deal.svg",
    "price": 45.06,
    "originalPrice": 57.64,
    "discountPercent": 21,
    "category": "General",
    "description": "\ud83c\udfaf Limited time offer on Amazon Canada Deals: Save 33% on Mini Chainsaw + 50% on Women\u2019s Shirts + More. Act fast before it's gone!",
    "affiliateUrl": "https://amazon.ca/",
    "featured": true,
    "dateAdded": "2025-08-07"
  },
  {
    "id": "amazoncanadadealssav",
    "title": "Amazon Canada Deals: Save 45% on 3 in 1 Wireless Charger + 50% on Women\u2019s Summer Casual Dress + More",
    "imageUrl": "/placeholder-deal.svg",
    "price": 43.31,
    "originalPrice": 61.51,
    "discountPercent": 29,
    "category": "General",
    "description": "\ud83c\udfaf Limited time offer on Amazon Canada Deals: Save 45% on 3 in 1 Wireless Charger + 50% on Women\u2019s Summer Casual Dress + More. Act fast before it's gone!",
    "affiliateUrl": "https://amazon.ca/",
    "featured": true,
    "dateAdded": "2025-08-07"
  }
]