[
  {
    "id": "amazoncanadadealssav",
    "title": "Amazon Canada Deals: Save 63% on GKLPO Mini Projector with Built-in Apps Using Promo Code + More Offers",
    "imageUrl": "/placeholder-deal.svg",
    "price": 54.26,
    "originalPrice": 74.44,
    "discountPercent": 27,
    "category": "General",
    "description": "\ud83c\udfaf Limited time offer on Amazon Canada Deals: Save 63% on GKLPO Mini Projector with Built-in Apps Using Promo Code + More Offers. Act fast before it's gone!",
    "affiliateUrl": "https://amazon.ca/",
    "featured": true,
    "dateAdded": "2025-08-17"
  },
  {
    "id": "amazoncanadadealssav",
    "title": "Amazon Canada Deals: Save 10% on Portable Electric Lunch Box Food Heater + More",
    "imageUrl": "/placeholder-deal.svg",
    "price": 77.09,
    "originalPrice": 122.71,
    "discountPercent": 37,
    "category": "General",
    "description": "\u26a1 Hot savings on Amazon Canada Deals: Save 10% on Portable Electric Lunch Box Food Heater + More! Don't miss this incredible offer.",
    "affiliateUrl": "https://amazon.ca/",
    "featured": true,
    "dateAdded": "2025-08-17"
  },
  {
    "id": "amazoncanadadealssav",
    "title": "Amazon Canada Deals: Save 75% on\u00a0Treadmill + 73% on Cordless Stick Vacuum Cleaner + More",
    "imageUrl": "/placeholder-deal.svg",
    "price": 37.65,
    "originalPrice": 59.99,
    "discountPercent": 37,
    "category": "General",
    "description": "\ud83c\udfaf Limited time offer on Amazon Canada Deals: Save 75% on\u00a0Treadmill + 73% on Cordless Stick Vacuum Cleaner + More. Act fast before it's gone!",
    "affiliateUrl": "https://amazon.ca/",
    "featured": true,
    "dateAdded": "2025-08-17"
  },
  {
    "id": "bestbuycanadatechfes",
    "title": "Best Buy Canada: Tech Fest Sale Until August 17th",
    "imageUrl": "/placeholder-deal.svg",
    "price": 718.72,
    "originalPrice": 977.84,
    "discountPercent": 26,
    "category": "General",
    "description": "\u2b50 Customer favorite! Best Buy Canada: Tech Fest Sale Until August 17th delivers exceptional value.",
    "affiliateUrl": "https://bestbuy.ca/",
    "featured": true,
    "dateAdded": "2025-08-17"
  }
]