[
  {
    "id": "amazoncanadadealssav",
    "title": "Amazon Canada Deals: Save 42% on Air Purifier + 50% on Vegetable Chopper Cutter + More",
    "imageUrl": "/placeholder-deal.svg",
    "price": 57.26,
    "originalPrice": 76.73,
    "discountPercent": 25,
    "category": "General",
    "description": "\u26a1 Hot savings on Amazon Canada Deals: Save 42% on Air Purifier + 50% on Vegetable Chopper Cutter + More! Don't miss this incredible offer.",
    "affiliateUrl": "https://amazon.ca/",
    "featured": true,
    "dateAdded": "2025-08-09"
  },
  {
    "id": "loblawsontarioget100",
    "title": "Loblaws Ontario: Get 10,000 PC Optimum Points For Every $40 Spent on Baby Items August 12th & 13th + Flyer Deals",
    "imageUrl": "/placeholder-deal.svg",
    "price": 50.21,
    "originalPrice": 76.18,
    "discountPercent": 34,
    "category": "General",
    "description": "\ud83c\udfaf Limited time offer on Loblaws Ontario: Get 10,000 PC Optimum Points For Every $40 Spent on Baby Items August 12th & 13th + Flyer Deals. Act fast before it's gone!",
    "affiliateUrl": "https://loblaws.ca/",
    "featured": true,
    "dateAdded": "2025-08-09"
  },
  {
    "id": "amazoncanadadealssav",
    "title": "Amazon Canada Deals: Save 84% on Steamer Iron for Clothes + 34% on Women\u2019s Summer Casual Dresses + More",
    "imageUrl": "/placeholder-deal.svg",
    "price": 72.29,
    "originalPrice": 88.78,
    "discountPercent": 18,
    "category": "General",
    "description": "\ud83d\udd25 Amazing deal on Amazon Canada Deals: Save 84% on Steamer Iron for Clothes + 34% on Women\u2019s Summer Casual Dresses + More! Premium quality at an unbeatable price.",
    "affiliateUrl": "https://amazon.ca/",
    "featured": true,
    "dateAdded": "2025-08-09"
  },
  {
    "id": "shoppersdrugmartcana",
    "title": "Shoppers Drug Mart Canada: 20x The PC Optimum Points August 8th \u2013 10th + More",
    "imageUrl": "/placeholder-deal.svg",
    "price": 49.21,
    "originalPrice": 77.47,
    "discountPercent": 36,
    "category": "General",
    "description": "\ud83c\udfaf Limited time offer on Shoppers Drug Mart Canada: 20x The PC Optimum Points August 8th \u2013 10th + More. Act fast before it's gone!",
    "affiliateUrl": "https://shoppersdrugmart.ca/",
    "featured": true,
    "dateAdded": "2025-08-09"
  },
  {
    "id": "amazoncanadadealssav",
    "title": "Amazon Canada Deals: Save 60% on MAXGROOM PRO 7D Electric\u00a0Head Shaver for Bald Men + More",
    "imageUrl": "/placeholder-deal.svg",
    "price": 63.62,
    "originalPrice": 95.51,
    "discountPercent": 33,
    "category": "General",
    "description": "\ud83d\udcab Discover why thousands love Amazon Canada Deals: Save 60% on MAXGROOM PRO 7D Electric\u00a0Head Shaver for Bald Men + More. Quality meets value!",
    "affiliateUrl": "https://amazon.ca/",
    "featured": true,
    "dateAdded": "2025-08-09"
  }
]